karta_benchmarks/__init__.py
karta_benchmarks/context_engine.py
karta_benchmarks/evaluation_datasets/__init__.py
karta_benchmarks/evaluation_datasets/ecommerce/__init__.py
karta_benchmarks/evaluation_datasets/ecommerce/data_factory/__init__.py
karta_benchmarks/evaluation_datasets/ecommerce/data_factory/factory.py
karta_benchmarks/evaluation_datasets/ecommerce/function_factory/__init__.py
karta_benchmarks/evaluation_datasets/ecommerce/function_factory/factory.py
karta_benchmarks/evaluation_datasets/ecommerce/knowledge_base/__init__.py
karta_benchmarks/evaluation_datasets/ecommerce/knowledge_base/get_knowledge_base.py
karta_benchmarks/evaluation_datasets/ecommerce/raw_data/__init__.py
karta_benchmarks/evaluation_datasets/ecommerce/schemas/__init__.py
karta_benchmarks/evaluation_datasets/ecommerce/schemas/schemas.py
karta_benchmarks/evaluation_datasets/ecommerce/sop/__init__.py
karta_benchmarks/evaluation_datasets/ecommerce/sop/get_sops.py
karta_benchmarks/evaluation_datasets/ecommerce/task_factory/__init__.py
karta_benchmarks/evaluation_datasets/ecommerce/task_factory/factory.py
karta_benchmarks/evaluation_datasets/ecommerce/task_factory/task_1.py
karta_benchmarks/evaluation_datasets/ecommerce/task_factory/task_2.py
karta_benchmarks/evaluation_datasets/ecommerce/task_factory/task_3.py
karta_benchmarks/general_helpers/__init__.py
karta_benchmarks/general_helpers/collect_schemas.py
karta_benchmarks/general_helpers/collect_tasks.py
karta_benchmarks/general_helpers/get_frame_info.py
karta_benchmarks/namespaces/__init__.py
karta_benchmarks/namespaces/domains.py
karta_benchmarks-0.0.5.dist-info/LICENSE
karta_benchmarks-0.0.5.dist-info/METADATA
karta_benchmarks-0.0.5.dist-info/WHEEL
karta_benchmarks-0.0.5.dist-info/top_level.txt
karta_benchmarks-0.0.5.dist-info/RECORD
