Metadata-Version: 2.2
Name: karta_benchmarks
Version: 0.0.5
Summary: The Karta Context Engine
Home-page: https://github.com/getkarta/KartaBenchmarkCaseDetails
Author: GetKart.ai
Author-email: Karta <signup@karta.ai>
Requires-Python: >=3.6
License-File: LICENSE
Dynamic: author
Dynamic: home-page
Dynamic: requires-python
